wagtailmenupage/__init__.py
wagtailmenupage/apps.py
wagtailmenupage/models.py
wagtailmenupage/migrations/0001_initial.py
wagtailmenupage/migrations/0002_rename_db_table_and_labels.py
wagtailmenupage/migrations/__init__.py
wagtailmenupage/templates/navigation/example_menu.html
wagtailmenupage/templatetags/__init__.py
wagtailmenupage/templatetags/menupage_tags.py
wagtailmenupage-1.1.1.dist-info/licenses/LICENSE
wagtailmenupage-1.1.1.dist-info/METADATA
wagtailmenupage-1.1.1.dist-info/WHEEL
wagtailmenupage-1.1.1.dist-info/top_level.txt
wagtailmenupage-1.1.1.dist-info/RECORD
