Metadata-Version: 2.4
Name: wagtailmenupage
Version: 1.1.1
Summary: A Wagtail page model for creating menu pages.
Author-email: Jack Whitworth <jack@jackwhitworth.com>
License-Expression: MIT
Project-URL: Source, https://github.com/jmwhitworth/wagtailmenupage
Project-URL: Changelog, https://github.com/jmwhitworth/wagtailmenupage/blob/main/changelog.md
Keywords: wagtail,menu,page,pages
Classifier: Framework :: Django
Classifier: Framework :: Wagtail
Classifier: Framework :: Wagtail :: 6
Classifier: Framework :: Wagtail :: 7
Classifier: Intended Audience :: Developers
Classifier: Natural Language :: English
Classifier: Operating System :: OS Independent
Classifier: Programming Language :: Python :: 3
Classifier: Programming Language :: Python :: 3 :: Only
Classifier: Topic :: Internet :: WWW/HTTP :: Site Management
Requires-Python: >=3.9
License-File: LICENSE
Requires-Dist: wagtail<8.0,>=5.0
Dynamic: license-file
